flopco/__init__.py
flopco/compute_layer_flops.py
flopco/flopco.py
flopco_pytorch-0.1.4.dist-info/LICENSE.txt
flopco_pytorch-0.1.4.dist-info/METADATA
flopco_pytorch-0.1.4.dist-info/WHEEL
flopco_pytorch-0.1.4.dist-info/top_level.txt
flopco_pytorch-0.1.4.dist-info/RECORD
