Metadata-Version: 2.1
Name: flopco-pytorch
Version: 0.1.4
Summary: FLOPs and other statistics COunter for Pytorch neural networks
Home-page: https://github.com/juliagusak/flopco-pytorch
Author: Julia Gusak
Author-email: julgusak@gmail.com
License: MIT
Download-URL: https://github.com/juliagusak/flopco-pytorch/archive/v0.1.4.tar.gz
Keywords: pytorch,flops,macs,neural-networks,cnn
Platform: UNKNOWN
